determystic/__init__.py
determystic/disk_config.py
determystic/entrypoint.py
determystic/external.py
determystic/io.py
determystic/isolated_env.py
determystic/logging.py
determystic/__tests__/agents/__init__.py
determystic/__tests__/agents/test_create_validator.py
determystic/__tests__/cli/__init__.py
determystic/__tests__/configs/__init__.py
determystic/__tests__/configs/test_base.py
determystic/__tests__/configs/test_project.py
determystic/__tests__/configs/test_system.py
determystic/__tests__/validators/__init__.py
determystic/__tests__/validators/test_dynamic_ast.py
determystic/__tests__/validators/test_hanging_functions.py
determystic/__tests__/validators/test_static_analysis.py
determystic/agents/__init__.py
determystic/agents/create_validator.py
determystic/cli/__init__.py
determystic/cli/common.py
determystic/cli/configure.py
determystic/cli/list_validators.py
determystic/cli/new_validator.py
determystic/cli/validate.py
determystic/configs/base.py
determystic/configs/project.py
determystic/configs/system.py
determystic/validators/__init__.py
determystic/validators/base.py
determystic/validators/dynamic_ast.py
determystic/validators/hanging_functions.py
determystic/validators/static_analysis.py
determystic-0.1.3.dist-info/METADATA
determystic-0.1.3.dist-info/WHEEL
determystic-0.1.3.dist-info/entry_points.txt
determystic-0.1.3.dist-info/RECORD
