Metadata-Version: 2.4
Name: determystic
Version: 0.1.3
Summary: Add your description here
Requires-Python: >=3.12
Requires-Dist: anthropic>=0.39.0
Requires-Dist: click>=8.1.0
Requires-Dist: prompt-toolkit>=3.0.0
Requires-Dist: pydantic-ai>=0.0.14
Requires-Dist: pydantic-settings>=2.0.0
Requires-Dist: pytest-asyncio>=0.24.0
Requires-Dist: pytest>=8.0.0
Requires-Dist: pyyaml>=6.0.0
Requires-Dist: rich>=13.0.0
Requires-Dist: ruff>=0.7.0
Requires-Dist: tomli-w>=1.0.0
Requires-Dist: ty
